{
	"name": "Level0",
	"layers": [
		{
			"name": "Grid",
			"overriden": 0,
			"subLayers": [],
			"instances": [
				{
					"type": "Tilemap",
					"properties": {
						"initially-visible": true,
						"tile-width": 64,
						"tile-height": 64,
						"tile-x-offset": 0,
						"tile-y-offset": 0,
						"tile-x-spacing": 0,
						"tile-y-spacing": 0,
						"tile-x-drawing-offset": 0,
						"tile-y-drawing-offset": 0,
						"drawing-mode": "top-to-right"
					},
					"uid": 508238,
					"instanceVariables": {},
					"behaviors": {
						"NoSave": {
							"properties": {}
						},
						"Solid": {
							"properties": {
								"enabled": true,
								"tags": ""
							}
						},
						"ScrollTo": {
							"properties": {
								"enabled": true
							}
						}
					},
					"ownData": {
						"tilemapData": {
							"width": 25,
							"height": 11,
							"max-width": 50,
							"max-height": 23,
							"data": "1,2,22x1,2,22x1,2,22x1,2,22x1,2,22x1,2,22x1,2,22x1,2,22x1,8x2,22x1,2,22x1,2,22x1,2,22x1,2,2x1,4x2,16x1,2,5x1,2,16x1,2,5x1,2,15x1,2x2,5x1,2,15x1,2,6x1,2,15x1,2,6x1,2,15x1,2,6x1,2,15x1,2,6x1,2,15x1,2,6x1,2,22x1,2,22x1,2,22x1,2,22x1,2,22x1,2,22x1,2,537x1"
						},
						"tile-width": 64,
						"tile-height": 64,
						"tile-x-offset": 0,
						"tile-y-offset": 0,
						"tile-x-spacing": 0,
						"tile-y-spacing": 0
					},
					"world": {
						"x": 0,
						"y": 0,
						"width": 1600,
						"height": 753,
						"originX": 0,
						"originY": 0,
						"color": [
							1,
							1,
							1,
							1
						],
						"zElevation": 0
					}
				}
			],
			"sid": 484369744225115,
			"effectTypes": [],
			"isInitiallyVisible": true,
			"isInitiallyInteractive": true,
			"color": [
				1,
				1,
				1,
				1
			],
			"backgroundColor": [
				0.3686274509803922,
				0.3686274509803922,
				0.3686274509803922,
				1
			],
			"isTransparent": false,
			"parallaxX": 1,
			"parallaxY": 1,
			"scaleRate": 1,
			"forceOwnTexture": false,
			"renderingMode": "3d",
			"drawOrder": "z-order",
			"useRenderCells": false,
			"blendMode": "normal",
			"zElevation": 0,
			"global": false
		},
		{
			"name": "Enemies",
			"overriden": 0,
			"subLayers": [],
			"instances": [
				{
					"type": "EndPoint",
					"properties": {
						"initially-visible": true,
						"initial-animation": "Animation 1",
						"initial-frame": 0,
						"enable-collisions": false,
						"live-preview": false
					},
					"uid": 847115,
					"instanceVariables": {},
					"behaviors": {},
					"world": {
						"x": 1311,
						"y": 481,
						"width": 32,
						"height": 32,
						"originX": 0.5,
						"originY": 0.5,
						"color": [
							1,
							1,
							1,
							1
						],
						"angle": 0,
						"zElevation": 0
					}
				},
				{
					"type": "SpawnPoint",
					"properties": {
						"initially-visible": true,
						"initial-animation": "Animation 1",
						"initial-frame": 0,
						"enable-collisions": false,
						"live-preview": false
					},
					"uid": 337195,
					"instanceVariables": {
						"SpawnDelay": 1
					},
					"behaviors": {
						"Timer": {
							"properties": {}
						},
						"NoSave": {
							"properties": {}
						},
						"Flash": {
							"properties": {}
						}
					},
					"world": {
						"x": 32.500905395204455,
						"y": 97.85433105835341,
						"width": 52.05093772765673,
						"height": 52.05093772765673,
						"originX": 0.5,
						"originY": 0.5,
						"color": [
							1,
							1,
							1,
							1
						],
						"angle": 0,
						"zElevation": 0
					}
				}
			],
			"sid": 202892845038904,
			"effectTypes": [],
			"isInitiallyVisible": true,
			"isInitiallyInteractive": true,
			"color": [
				1,
				1,
				1,
				1
			],
			"backgroundColor": [
				0.3686274509803922,
				0.3686274509803922,
				0.3686274509803922,
				1
			],
			"isTransparent": true,
			"parallaxX": 1,
			"parallaxY": 1,
			"scaleRate": 1,
			"forceOwnTexture": false,
			"renderingMode": "3d",
			"drawOrder": "z-order",
			"useRenderCells": false,
			"blendMode": "normal",
			"zElevation": 0,
			"global": false
		},
		{
			"name": "UI",
			"overriden": 0,
			"subLayers": [],
			"instances": [],
			"sid": 200564551725230,
			"effectTypes": [],
			"isInitiallyVisible": true,
			"isInitiallyInteractive": true,
			"color": [
				1,
				1,
				1,
				1
			],
			"backgroundColor": [
				0.3686274509803922,
				0.3686274509803922,
				0.3686274509803922,
				1
			],
			"isTransparent": true,
			"parallaxX": 1,
			"parallaxY": 1,
			"scaleRate": 1,
			"forceOwnTexture": false,
			"renderingMode": "3d",
			"drawOrder": "z-order",
			"useRenderCells": false,
			"blendMode": "normal",
			"zElevation": 0,
			"global": false
		}
	],
	"sid": 503960423826650,
	"nonworld-instances": [],
	"effectTypes": [],
	"width": 1600,
	"height": 720,
	"unboundedScrolling": false,
	"vpX": 0.5,
	"vpY": 0.5,
	"projection": "orthographic",
	"eventSheet": "TowerSheet"
}